{"frames":{"startbutton1":{"frame":{"x":4097,"y":2734,"w":336,"h":94},"rotated":false,"trimmed":false,"spriteSourceSize":{"x":0,"y":0,"w":336,"h":94},"sourceSize":{"w":336,"h":94}},"startbutton2":{"frame":{"x":4801,"y":7344,"w":967,"h":386},"rotated":false,"trimmed":false,"spriteSourceSize":{"x":0,"y":0,"w":967,"h":386},"sourceSize":{"w":967,"h":386}},"startbutton3":{"frame":{"x":4097,"y":2829,"w":2602,"h":166},"rotated":false,"trimmed":false,"spriteSourceSize":{"x":0,"y":0,"w":2602,"h":166},"sourceSize":{"w":2602,"h":166}},"startbutton4":{"frame":{"x":0,"y":2701,"w":4544,"h":32},"rotated":false,"trimmed":false,"spriteSourceSize":{"x":0,"y":0,"w":4544,"h":32},"sourceSize":{"w":4544,"h":32}},"continuebutton1":{"frame":{"x":4097,"y":2996,"w":534,"h":95},"rotated":false,"trimmed":false,"spriteSourceSize":{"x":0,"y":0,"w":534,"h":95},"sourceSize":{"w":534,"h":95}},"continuebutton3":{"frame":{"x":4097,"y":5454,"w":2625,"h":137},"rotated":false,"trimmed":false,"spriteSourceSize":{"x":0,"y":0,"w":2625,"h":137},"sourceSize":{"w":2625,"h":137}},"continuebutton2":{"frame":{"x":4097,"y":5039,"w":1445,"h":414},"rotated":false,"trimmed":false,"spriteSourceSize":{"x":0,"y":0,"w":1445,"h":414},"sourceSize":{"w":1445,"h":414}},"title":{"frame":{"x":0,"y":7344,"w":4800,"h":2700},"rotated":false,"trimmed":false,"spriteSourceSize":{"x":0,"y":0,"w":4800,"h":2700},"sourceSize":{"w":4800,"h":2700}},"scoretitleBG":{"frame":{"x":0,"y":2734,"w":4096,"h":2304},"rotated":false,"trimmed":false,"spriteSourceSize":{"x":0,"y":0,"w":4096,"h":2304},"sourceSize":{"w":4096,"h":2304}},"titleBG":{"frame":{"x":0,"y":5039,"w":4096,"h":2304},"rotated":false,"trimmed":false,"spriteSourceSize":{"x":0,"y":0,"w":4096,"h":2304},"sourceSize":{"w":4096,"h":2304}},"startraninbowanimation1":{"frame":{"x":0,"y":10045,"w":7133,"h":2700},"rotated":false,"trimmed":false,"spriteSourceSize":{"x":0,"y":0,"w":7133,"h":2700},"sourceSize":{"w":7133,"h":2700}},"startraninbowanimation2":{"frame":{"x":0,"y":0,"w":7133,"h":2700},"rotated":false,"trimmed":false,"spriteSourceSize":{"x":0,"y":0,"w":7133,"h":2700},"sourceSize":{"w":7133,"h":2700}}},"meta":{"app":"https://www.leshylabs.com/apps/sstool/","version":"Leshy SpriteSheet Tool v0.8.4","image":"titleImages.png","size":{"w":7133,"h":12745},"scale":1}}